empaia_app_test_suite/__init__.py
empaia_app_test_suite/cli.py
empaia_app_test_suite/cli_definitions/__init__.py
empaia_app_test_suite/cli_definitions/apps_cli.py
empaia_app_test_suite/cli_definitions/cases_cli.py
empaia_app_test_suite/cli_definitions/jobs_cli.py
empaia_app_test_suite/cli_definitions/main_cli.py
empaia_app_test_suite/cli_definitions/services_cli.py
empaia_app_test_suite/cli_definitions/slides_cli.py
empaia_app_test_suite/commands/__init__.py
empaia_app_test_suite/commands/apps_commands.py
empaia_app_test_suite/commands/cases_commands.py
empaia_app_test_suite/commands/helper/__init__.py
empaia_app_test_suite/commands/helper/app_helper.py
empaia_app_test_suite/commands/helper/data_helper.py
empaia_app_test_suite/commands/helper/job_helper.py
empaia_app_test_suite/commands/helper/job_validation_helper.py
empaia_app_test_suite/commands/helper/wsi_helper.py
empaia_app_test_suite/commands/jobs_commands.py
empaia_app_test_suite/commands/services_commands.py
empaia_app_test_suite/commands/slides_commands.py
empaia_app_test_suite/constants.py
empaia_app_test_suite/custom_models.py
empaia_app_test_suite/models/.git
empaia_app_test_suite/models/.gitignore
empaia_app_test_suite/models/.gitlab/issue_templates/story_qa_level_1.md
empaia_app_test_suite/models/.gitlab/merge_request_templates/merge_request_qa_level_1.md
empaia_app_test_suite/models/.gitlab-ci.yml
empaia_app_test_suite/models/CHANGELOG.md
empaia_app_test_suite/models/LICENSE
empaia_app_test_suite/models/README.md
empaia_app_test_suite/models/__init__.py
empaia_app_test_suite/models/commons.py
empaia_app_test_suite/models/fhir/__init__.py
empaia_app_test_suite/models/fhir/commons.py
empaia_app_test_suite/models/fhir/questionnaire_responses.py
empaia_app_test_suite/models/fhir/questionnaires.py
empaia_app_test_suite/models/marketplace/__init__.py
empaia_app_test_suite/models/marketplace/app.py
empaia_app_test_suite/models/poetry.lock
empaia_app_test_suite/models/pyproject.toml
empaia_app_test_suite-3.7.0.dist-info/LICENSE
empaia_app_test_suite-3.7.0.dist-info/METADATA
empaia_app_test_suite-3.7.0.dist-info/WHEEL
empaia_app_test_suite-3.7.0.dist-info/entry_points.txt
empaia_app_test_suite-3.7.0.dist-info/RECORD
