Metadata-Version: 2.1
Name: empaia-app-test-suite
Version: 3.7.0
Summary: The EMPAIA App Test Suite (EATS)
Home-page: https://developer.empaia.org/app_developer_docs/#/
License: MIT
Author: EMPAIA
Author-email: support@empaia.org
Maintainer: EMPAIA
Maintainer-email: support@empaia.org
Requires-Python: >=3.10,<4.0
Classifier: Development Status :: 5 - Production/Stable
Classifier: Intended Audience :: Developers
Classifier: Intended Audience :: Healthcare Industry
Classifier: Intended Audience :: Science/Research
Classifier: License :: OSI Approved :: MIT License
Classifier: Operating System :: MacOS
Classifier: Operating System :: Microsoft :: Windows :: Windows 10
Classifier: Operating System :: POSIX
Classifier: Programming Language :: Python :: 3
Classifier: Programming Language :: Python :: 3.10
Classifier: Programming Language :: Python :: 3.11
Classifier: Programming Language :: Python :: 3.12
Classifier: Topic :: Software Development
Classifier: Topic :: Software Development :: Testing
Requires-Dist: PyYAML (>=6.0,<7.0)
Requires-Dist: docker (>=7.0.0,<8.0.0)
Requires-Dist: jsonschema (>=4.4.0,<5.0.0)
Requires-Dist: prettytable (>=3.2.0,<4.0.0)
Requires-Dist: pydantic (>=2.5.0,<3.0.0)
Requires-Dist: pydantic-settings (>=2.0.3,<3.0.0)
Requires-Dist: requests (==2.32.3)
Requires-Dist: toml (>=0.10.2,<0.11.0)
Requires-Dist: typer[all] (>=0.12.0,<0.13.0)
Project-URL: Bug Tracker, https://gitlab.com/empaia/integration/empaia-app-test-suite/-/issues
Project-URL: Documentation, https://developer.empaia.org/app_developer_docs/#/
Project-URL: Repository, https://gitlab.com/empaia/integration/empaia-app-test-suite
